pfund_kit/__init__.py
pfund_kit/aliase.py
pfund_kit/cli/__init__.py
pfund_kit/cli/commands/__init__.py
pfund_kit/cli/commands/config.py
pfund_kit/cli/commands/doc.py
pfund_kit/cli/commands/docker_compose.py
pfund_kit/cli/commands/remove.py
pfund_kit/cli/main.py
pfund_kit/cli/utils.py
pfund_kit/config.py
pfund_kit/enums/notebook_type.py
pfund_kit/logging/__init__.py
pfund_kit/logging/configurator.py
pfund_kit/logging/filters/__init__.py
pfund_kit/logging/filters/trimmed_path_filter.py
pfund_kit/logging/formatters/__init__.py
pfund_kit/logging/formatters/ansi_styles.py
pfund_kit/logging/formatters/colored_formatter.py
pfund_kit/logging/handlers/__init__.py
pfund_kit/logging/handlers/compressed_timed_rotating_file_handler.py
pfund_kit/logging/handlers/lazy_handler.py
pfund_kit/logging/handlers/telegram_handler.py
pfund_kit/logging/loggers/__init__.py
pfund_kit/logging/loggers/colored_logger.py
pfund_kit/paths.py
pfund_kit/pfund_shell/help.py
pfund_kit/pfund_shell/main.py
pfund_kit/pfund_shell/shell_group.py
pfund_kit/pfund_shell/toolbar.py
pfund_kit/pfund_shell/tutorial.py
pfund_kit/pfund_shell/utils.py
pfund_kit/style.py
pfund_kit/utils/__init__.py
pfund_kit/utils/function.py
pfund_kit/utils/progress_bar.py
pfund_kit/utils/singleton.py
pfund_kit/utils/temporal.py
pfund_kit/utils/text.py
pfund_kit/utils/toml.py
pfund_kit/utils/yaml.py
pfund_kit-0.1.2.dist-info/WHEEL
pfund_kit-0.1.2.dist-info/entry_points.txt
pfund_kit-0.1.2.dist-info/METADATA
pfund_kit-0.1.2.dist-info/RECORD
