Metadata-Version: 2.4
Name: pfund-kit
Version: 0.1.2
Summary: Configuration, CLI, and shared utilities for packages in pfund's ecosystem
Author: Stephen Yau
Author-email: Stephen Yau <softwareentrepreneer+pfund-kit@gmail.com>
License-Expression: Apache-2.0
Requires-Dist: rich>=14.2.0
Requires-Dist: tqdm>=4.67.1
Requires-Dist: click>=8.2.1
Requires-Dist: trogon>=0.6.0
Requires-Dist: pyyaml>=6.0.3
Requires-Dist: tomlkit>=0.13.3
Requires-Dist: packaging>=25.0
Requires-Dist: platformdirs>=4.2.2
Requires-Dist: python-dotenv>=1.2.1
Requires-Dist: prompt-toolkit>=3.0.51
Requires-Python: >=3.11
Project-URL: homepage, https://pfund.ai
Project-URL: repository, https://github.com/PFund-Software-Ltd/pfund-kit
